rhylthyme_cli_runner/__init__.py
rhylthyme_cli_runner/cli.py
rhylthyme_cli_runner/environment_icons.py
rhylthyme_cli_runner/environment_loader.py
rhylthyme_cli_runner/environment_schemas.py
rhylthyme_cli_runner/program_planner.py
rhylthyme_cli_runner/program_runner.py
rhylthyme_cli_runner/validate_program.py
rhylthyme_cli_runner-0.1.2a0.dist-info/METADATA
rhylthyme_cli_runner-0.1.2a0.dist-info/WHEEL
rhylthyme_cli_runner-0.1.2a0.dist-info/entry_points.txt
rhylthyme_cli_runner-0.1.2a0.dist-info/top_level.txt
rhylthyme_cli_runner-0.1.2a0.dist-info/RECORD
