Metadata-Version: 2.4
Name: rhylthyme-cli-runner
Version: 0.1.2a0
Summary: CLI runner for Rhylthyme real-time program schedules
Home-page: https://github.com/rhylthyme/rhylthyme-cli-runner
Author: Rhylthyme Team
Author-email: team@rhylthyme.org
Project-URL: Bug Reports, https://github.com/rhylthyme/rhylthyme-cli-runner/issues
Project-URL: Source, https://github.com/rhylthyme/rhylthyme-cli-runner
Project-URL: Documentation, https://github.com/rhylthyme/rhylthyme-cli-runner#readme
Keywords: real-time,scheduling,logistics,cli,validation
Classifier: Development Status :: 3 - Alpha
Classifier: Intended Audience :: Developers
Classifier: License :: OSI Approved :: Apache Software License
Classifier: Operating System :: OS Independent
Classifier: Programming Language :: Python :: 3
Classifier: Programming Language :: Python :: 3.8
Classifier: Programming Language :: Python :: 3.9
Classifier: Programming Language :: Python :: 3.10
Classifier: Programming Language :: Python :: 3.11
Classifier: Topic :: Software Development :: Libraries :: Python Modules
Classifier: Topic :: System :: Distributed Computing
Requires-Python: >=3.8
Requires-Dist: click>=8.0.0
Requires-Dist: jsonschema>=4.0.0
Requires-Dist: pyyaml>=6.0
Requires-Dist: colorama>=0.4.0
Requires-Dist: rhylthyme-spec>=0.1.0-alpha
Provides-Extra: dev
Requires-Dist: pytest>=6.0.0; extra == "dev"
Requires-Dist: pytest-cov>=2.10.0; extra == "dev"
Requires-Dist: pytest-mock>=3.0.0; extra == "dev"
Requires-Dist: pytest-xdist>=2.0.0; extra == "dev"
Requires-Dist: black>=21.0.0; extra == "dev"
Requires-Dist: flake8>=3.8.0; extra == "dev"
Requires-Dist: isort>=5.0.0; extra == "dev"
Requires-Dist: mypy>=0.800; extra == "dev"
Requires-Dist: responses>=0.12.0; extra == "dev"
Requires-Dist: freezegun>=1.0.0; extra == "dev"
Provides-Extra: docs
Requires-Dist: sphinx>=4.0.0; extra == "docs"
Requires-Dist: sphinx-rtd-theme>=1.0.0; extra == "docs"
Provides-Extra: build
Requires-Dist: build>=0.7.0; extra == "build"
Requires-Dist: twine>=3.4.0; extra == "build"
Dynamic: author
Dynamic: author-email
Dynamic: classifier
Dynamic: description
Dynamic: description-content-type
Dynamic: home-page
Dynamic: keywords
Dynamic: project-url
Dynamic: provides-extra
Dynamic: requires-dist
Dynamic: requires-python
Dynamic: summary
